melissa/__init__.py
melissa/const.py
melissa/exceptions.py
py_melissa_climate-3.0.3.dist-info/licenses/LICENSE.md
py_melissa_climate-3.0.3.dist-info/METADATA
py_melissa_climate-3.0.3.dist-info/WHEEL
py_melissa_climate-3.0.3.dist-info/top_level.txt
py_melissa_climate-3.0.3.dist-info/RECORD
