Metadata-Version: 2.4
Name: py-melissa-climate
Version: 3.0.3
Summary: Api wrapper for Melissa Climate http://seemelissa.com
Author-email: Magnus Knutas <magnusknutas@gmail.com>
Maintainer-email: Magnus Knutas <magnusknutas@gmail.com>
License-Expression: MIT
Project-URL: Bug Tracker, https://github.com/kennedyshead/py-melissa-climate/issues
Project-URL: Changelog, https://github.com/kennedyshead/py-melissa-climate/blob/master/CHANGELOG.md
Project-URL: Documentation, https://github.com/kennedyshead/py-melissa-climate/blob/master/README.md
Project-URL: Homepage, https://github.com/kennedyshead/py-melissa-climate
Project-URL: Repository, https://github.com/kennedyshead/py-melissa-climate.git
Keywords: Melissa Climate,bobby,development,hass,homeassistant,iot,mClimate,melissa
Classifier: Development Status :: 3 - Alpha
Classifier: Intended Audience :: Developers
Classifier: Programming Language :: Python :: 3
Classifier: Topic :: Software Development :: Libraries
Requires-Python: >=3.12
License-File: LICENSE.md
Requires-Dist: aiohttp
Provides-Extra: dev
Dynamic: license-file
